[
  {
    "full_name": "nuxt/image",
    "stargazers_count": 614,
    "open_issues_count": 150,
    "forks_count": 126
  },
  {
    "full_name": "lydiahallie/javascript-questions",
    "stargazers_count": 44547,
    "open_issues_count": 86,
    "forks_count": 6241
  },
  {
    "full_name": "FreeTubeApp/FreeTube",
    "stargazers_count": 5432,
    "open_issues_count": 430,
    "forks_count": 376
  },
  {
    "full_name": "hallee/eslint-action",
    "stargazers_count": 120,
    "open_issues_count": 4,
    "forks_count": 40
  },
  {
    "full_name": "dom96/jester",
    "stargazers_count": 1291,
    "open_issues_count": 58,
    "forks_count": 107
  },
  {
    "full_name": "vikpe/mongoose-mpath",
    "stargazers_count": 58,
    "open_issues_count": 2,
    "forks_count": 13
  },
  {
    "full_name": "hotwired/stimulus",
    "stargazers_count": 11360,
    "open_issues_count": 30,
    "forks_count": 336
  },
  {
    "full_name": "nolimits4web/swiper",
    "stargazers_count": 31449,
    "open_issues_count": 215,
    "forks_count": 9625
  },
  {
    "full_name": "twbs/bootstrap",
    "stargazers_count": 158013,
    "open_issues_count": 367,
    "forks_count": 76812
  },
  {
    "full_name": "grain-lang/grain",
    "stargazers_count": 2479,
    "open_issues_count": 195,
    "forks_count": 87
  },
  {
    "full_name": "jamiebuilds/unstated",
    "stargazers_count": 7799,
    "open_issues_count": 18,
    "forks_count": 314
  },
  {
    "full_name": "facebook/react",
    "stargazers_count": 189936,
    "open_issues_count": 974,
    "forks_count": 39127
  },
  {
    "full_name": "GeekyAnts/vue-native-core",
    "stargazers_count": 8360,
    "open_issues_count": 33,
    "forks_count": 320
  },
  {
    "full_name": "denoland/deno",
    "stargazers_count": 82986,
    "open_issues_count": 931,
    "forks_count": 4460
  },
  {
    "full_name": "razorpay/razorpay-dot-net",
    "stargazers_count": 8,
    "open_issues_count": 22,
    "forks_count": 29
  },
  {
    "full_name": "JsonCSharpClassGenerator/JsonCSharpClassGenerator",
    "stargazers_count": 80,
    "open_issues_count": 0,
    "forks_count": 38
  },
  {
    "full_name": "asika32764/vue2-animate",
    "stargazers_count": 1346,
    "open_issues_count": 7,
    "forks_count": 138
  },
  {
    "full_name": "nim-lang/Nim",
    "stargazers_count": 13007,
    "open_issues_count": 2273,
    "forks_count": 1319
  },
  {
    "full_name": "tabler/tabler",
    "stargazers_count": 26068,
    "open_issues_count": 62,
    "forks_count": 2990
  },
  {
    "full_name": "ramda/ramda",
    "stargazers_count": 22077,
    "open_issues_count": 128,
    "forks_count": 1422
  },
  {
    "full_name": "danieldiekmeier/vue-slide-up-down",
    "stargazers_count": 194,
    "open_issues_count": 8,
    "forks_count": 45
  },
  {
    "full_name": "sqlkata/querybuilder",
    "stargazers_count": 2294,
    "open_issues_count": 121,
    "forks_count": 392
  },
  {
    "full_name": "avelino/awesome-go",
    "stargazers_count": 82340,
    "open_issues_count": 21,
    "forks_count": 9948
  },
  {
    "full_name": "gin-gonic/gin",
    "stargazers_count": 60256,
    "open_issues_count": 532,
    "forks_count": 6693
  },
  {
    "full_name": "kelseyhightower/nocode",
    "stargazers_count": 52954,
    "open_issues_count": 4186,
    "forks_count": 4554
  },
  {
    "full_name": "jquery/esprima",
    "stargazers_count": 6535,
    "open_issues_count": 141,
    "forks_count": 784
  },
  {
    "full_name": "rstacruz/nprogress",
    "stargazers_count": 24347,
    "open_issues_count": 130,
    "forks_count": 1839
  },
  {
    "full_name": "OpenGenus/cosmos",
    "stargazers_count": 13042,
    "open_issues_count": 2487,
    "forks_count": 3432
  },
  {
    "full_name": "dhg/Skeleton",
    "stargazers_count": 18620,
    "open_issues_count": 140,
    "forks_count": 3134
  },
  {
    "full_name": "dotnet/blazor",
    "stargazers_count": 9347,
    "open_issues_count": 0,
    "forks_count": 680
  }
]